alttxt/__init__.py
alttxt/__main__.py
alttxt/enums.py
alttxt/generator.py
alttxt/glossary.py
alttxt/models.py
alttxt/parser.py
alttxt/phrases.py
alttxt/regionclass.py
alttxt/tokenmap.py
upset_alttxt-0.5.2.dist-info/LICENSE
upset_alttxt-0.5.2.dist-info/METADATA
upset_alttxt-0.5.2.dist-info/WHEEL
upset_alttxt-0.5.2.dist-info/top_level.txt
upset_alttxt-0.5.2.dist-info/RECORD
