Metadata-Version: 2.1
Name: upset-alttxt
Version: 0.5.2
Summary: Generates alt text for UpSet plots
Author: Visualization Design Lab
License: BSD3
Platform: unix
Platform: linux
Platform: osx
Platform: cygwin
Platform: win32
Classifier: Programming Language :: Python :: 3
Classifier: Programming Language :: Python :: 3 :: Only
Classifier: Programming Language :: Python :: 3.8
Requires-Python: >=3.8
License-File: LICENSE
Requires-Dist: numpy<2.0.0,>=1.20
Requires-Dist: scipy>=1.0.0
Requires-Dist: pydantic>=2.9.1
Provides-Extra: testing
Requires-Dist: flake8>=4.0; extra == "testing"
Requires-Dist: mypy>=1.0; extra == "testing"
Requires-Dist: pytest>=6.0; extra == "testing"
Requires-Dist: pytest-cov>=2.0; extra == "testing"
Requires-Dist: tox>=4.0; extra == "testing"
